performanceTester/__init__.py
performanceTester/perfTester.py
performTestingforTime-0.2.0.dist-info/METADATA
performTestingforTime-0.2.0.dist-info/WHEEL
performTestingforTime-0.2.0.dist-info/top_level.txt
performTestingforTime-0.2.0.dist-info/RECORD
