Metadata-Version: 2.1
Name: performTestingforTime
Version: 0.2.0
Summary: Tests the performance of functions according by time
Author: Tolga
